wasutest/__init__.py
wasutest/main.py
wasu_test-2.5.dist-info/LICENSE
wasu_test-2.5.dist-info/METADATA
wasu_test-2.5.dist-info/WHEEL
wasu_test-2.5.dist-info/top_level.txt
wasu_test-2.5.dist-info/RECORD
