Metadata-Version: 2.1
Name: wasu-test
Version: 2.5
Summary: wasu test framework
Home-page: UNKNOWN
Author: XiaoDong Chen
Author-email: 1346650911@qq.com
License: MIT
Platform: UNKNOWN
